MANIFEST.in
README.txt
setup.py
listspec/__init__.py
listspec/listhandleclass.py
spec_list_pp.egg-info/PKG-INFO
spec_list_pp.egg-info/SOURCES.txt
spec_list_pp.egg-info/dependency_links.txt
spec_list_pp.egg-info/top_level.txt